pyuavcan_v0/__init__.py
pyuavcan_v0/introspect.py
pyuavcan_v0/node.py
pyuavcan_v0/transport.py
pyuavcan_v0/version.py
pyuavcan_v0/app/__init__.py
pyuavcan_v0/app/dynamic_node_id.py
pyuavcan_v0/app/file_server.py
pyuavcan_v0/app/log_message_monitor.py
pyuavcan_v0/app/message_collector.py
pyuavcan_v0/app/node_monitor.py
pyuavcan_v0/driver/__init__.py
pyuavcan_v0/driver/common.py
pyuavcan_v0/driver/python_can.py
pyuavcan_v0/driver/slcan.py
pyuavcan_v0/driver/socketcan.py
pyuavcan_v0/driver/timestamp_estimator.py
pyuavcan_v0/dsdl/__init__.py
pyuavcan_v0/dsdl/common.py
pyuavcan_v0/dsdl/parser.py
pyuavcan_v0/dsdl/signature.py
pyuavcan_v0/dsdl/type_limits.py
pyuavcan_v0/dsdl_files/uavcan/CoarseOrientation.uavcan
pyuavcan_v0/dsdl_files/uavcan/Timestamp.uavcan
pyuavcan_v0/dsdl_files/uavcan/equipment/actuator/1010.ArrayCommand.uavcan
pyuavcan_v0/dsdl_files/uavcan/equipment/actuator/1011.Status.uavcan
pyuavcan_v0/dsdl_files/uavcan/equipment/actuator/Command.uavcan
pyuavcan_v0/dsdl_files/uavcan/equipment/ahrs/1000.Solution.uavcan
pyuavcan_v0/dsdl_files/uavcan/equipment/ahrs/1001.MagneticFieldStrength.uavcan
pyuavcan_v0/dsdl_files/uavcan/equipment/ahrs/1002.MagneticFieldStrength2.uavcan
pyuavcan_v0/dsdl_files/uavcan/equipment/ahrs/1003.RawIMU.uavcan
pyuavcan_v0/dsdl_files/uavcan/equipment/air_data/1020.TrueAirspeed.uavcan
pyuavcan_v0/dsdl_files/uavcan/equipment/air_data/1021.IndicatedAirspeed.uavcan
pyuavcan_v0/dsdl_files/uavcan/equipment/air_data/1025.AngleOfAttack.uavcan
pyuavcan_v0/dsdl_files/uavcan/equipment/air_data/1026.Sideslip.uavcan
pyuavcan_v0/dsdl_files/uavcan/equipment/air_data/1027.RawAirData.uavcan
pyuavcan_v0/dsdl_files/uavcan/equipment/air_data/1028.StaticPressure.uavcan
pyuavcan_v0/dsdl_files/uavcan/equipment/air_data/1029.StaticTemperature.uavcan
pyuavcan_v0/dsdl_files/uavcan/equipment/camera_gimbal/1040.AngularCommand.uavcan
pyuavcan_v0/dsdl_files/uavcan/equipment/camera_gimbal/1041.GEOPOICommand.uavcan
pyuavcan_v0-1.0.0.dev35.dist-info/LICENSE
pyuavcan_v0-1.0.0.dev35.dist-info/METADATA
pyuavcan_v0-1.0.0.dev35.dist-info/WHEEL
pyuavcan_v0-1.0.0.dev35.dist-info/top_level.txt
pyuavcan_v0-1.0.0.dev35.dist-info/RECORD
