Metadata-Version: 2.1
Name: pyuavcan-v0
Version: 1.0.0.dev35
Summary: UAVCAN/CAN v0 (legacy) implementation in Python. Checkout pyuavcan for v1 implementation.
Home-page: http://uavcan.org
Author: Pavel Kirienko, Ben Dyer
Author-email: maintainers@uavcan.org
License: MIT
Platform: UNKNOWN
Classifier: Development Status :: 3 - Alpha
Classifier: Intended Audience :: Developers
Classifier: Topic :: Software Development :: Libraries
Classifier: License :: OSI Approved :: MIT License
Classifier: Programming Language :: Python
License-File: LICENSE
